{
	"id": "1b7833ef-b659-4aab-a6a6-5f707d976d11",
	"name": "ClickUpEnv",
	"values": [
		{
			"key": "baseUrl",
			"value": "",
			"type": "default",
			"enabled": true
		},
		{
			"key": "token",
			"value": "",
			"type": "default",
			"enabled": true
		},
		{
			"key": "random_list_name",
			"value": "",
			"type": "any",
			"enabled": true
		},
		{
			"key": "updated_list_name",
			"value": "",
			"type": "any",
			"enabled": true
		}
	],
	"color": null,
	"_postman_variable_scope": "environment",
	"_postman_exported_at": "2026-06-14T22:03:44.769Z",
	"_postman_exported_using": "Postman/12.14.4"
}